odoo/addons/l10n_br_sped_ecd/README.rst
odoo/addons/l10n_br_sped_ecd/__init__.py
odoo/addons/l10n_br_sped_ecd/__manifest__.py
odoo/addons/l10n_br_sped_ecd/hooks.py
odoo/addons/l10n_br_sped_ecd/demo/demo_ecd.txt
odoo/addons/l10n_br_sped_ecd/i18n/l10n_br_sped_ecd.pot
odoo/addons/l10n_br_sped_ecd/models/__init__.py
odoo/addons/l10n_br_sped_ecd/models/sped_ecd.py
odoo/addons/l10n_br_sped_ecd/models/sped_ecd_spec_9.py
odoo/addons/l10n_br_sped_ecd/models/sped_mixin_ecd.py
odoo/addons/l10n_br_sped_ecd/readme/CONTRIBUTORS.md
odoo/addons/l10n_br_sped_ecd/readme/DESCRIPTION.md
odoo/addons/l10n_br_sped_ecd/readme/USAGE.md
odoo/addons/l10n_br_sped_ecd/security/ir.model.access.csv
odoo/addons/l10n_br_sped_ecd/static/description/icon.png
odoo/addons/l10n_br_sped_ecd/static/description/index.html
odoo/addons/l10n_br_sped_ecd/tests/__init__.py
odoo/addons/l10n_br_sped_ecd/tests/test_sped_ecd_generate.py
odoo/addons/l10n_br_sped_ecd/tests/test_sped_ecd_import.py
odoo/addons/l10n_br_sped_ecd/views/sped_ecd.xml
odoo_addon_l10n_br_sped_ecd-16.0.4.1.0.dist-info/METADATA
odoo_addon_l10n_br_sped_ecd-16.0.4.1.0.dist-info/WHEEL
odoo_addon_l10n_br_sped_ecd-16.0.4.1.0.dist-info/top_level.txt
odoo_addon_l10n_br_sped_ecd-16.0.4.1.0.dist-info/RECORD
